{
  "$schema": "https://developer.microsoft.com/json-schemas/fabric/item/report/definition/visualContainer/2.10.0/schema.json",
  "name": "6755a39fc625803182d0",
  "position": {
    "x": 31.142365097588986,
    "y": 29.896670493685406,
    "z": 7000,
    "height": 79.724454649827791,
    "width": 506.99770378874859,
    "tabOrder": 38000
  },
  "visual": {
    "visualType": "slicer",
    "query": {
      "queryState": {
        "Values": {
          "projections": [
            {
              "field": {
                "Column": {
                  "Expression": {
                    "SourceRef": {
                      "Entity": "UserStates"
                    }
                  },
                  "Property": "StartLocal"
                }
              },
              "queryRef": "UserStates.StartLocal",
              "nativeQueryRef": "StartLocal",
              "active": true
            }
          ]
        }
      },
      "sortDefinition": {
        "isDefaultSort": true
      }
    },
    "objects": {
      "data": [
        {
          "properties": {
            "mode": {
              "expr": {
                "Literal": {
                  "Value": "'Between'"
                }
              }
            }
          }
        }
      ],
      "general": [
        {
          "properties": {
            "outlineColor": {
              "solid": {
                "color": {
                  "expr": {
                    "Literal": {
                      "Value": "'#888888'"
                    }
                  }
                }
              }
            },
            "responsive": {
              "expr": {
                "Literal": {
                  "Value": "false"
                }
              }
            },
            "orientation": {
              "expr": {
                "Literal": {
                  "Value": "1D"
                }
              }
            }
          }
        }
      ],
      "header": [
        {
          "properties": {
            "show": {
              "expr": {
                "Literal": {
                  "Value": "false"
                }
              }
            }
          }
        }
      ],
      "date": [
        {
          "properties": {
            "textSize": {
              "expr": {
                "Literal": {
                  "Value": "12D"
                }
              }
            }
          }
        }
      ],
      "slider": [
        {
          "properties": {
            "color": {
              "solid": {
                "color": {
                  "expr": {
                    "ThemeDataColor": {
                      "ColorId": 1,
                      "Percent": 0
                    }
                  }
                }
              }
            }
          }
        }
      ]
    },
    "visualContainerObjects": {
      "title": [
        {
          "properties": {
            "show": {
              "expr": {
                "Literal": {
                  "Value": "false"
                }
              }
            },
            "text": {
              "expr": {
                "Literal": {
                  "Value": "'Date Range'"
                }
              }
            },
            "titleWrap": {
              "expr": {
                "Literal": {
                  "Value": "false"
                }
              }
            },
            "fontColor": {
              "solid": {
                "color": {
                  "expr": {
                    "Literal": {
                      "Value": "'#5A5B5C'"
                    }
                  }
                }
              }
            },
            "fontFamily": {
              "expr": {
                "Literal": {
                  "Value": "'''Segoe UI'', wf_segoe-ui_normal, helvetica, arial, sans-serif'"
                }
              }
            }
          }
        }
      ],
      "background": [
        {
          "properties": {
            "show": {
              "expr": {
                "Literal": {
                  "Value": "false"
                }
              }
            }
          }
        }
      ],
      "visualHeader": [
        {
          "properties": {
            "showTooltipButton": {
              "expr": {
                "Literal": {
                  "Value": "false"
                }
              }
            }
          }
        }
      ]
    },
    "drillFilterOtherVisuals": true
  },
  "parentGroupName": "8189a7adc92b3099c095"
}