{
  "$schema": "https://developer.microsoft.com/json-schemas/fabric/item/report/definition/visualContainer/2.10.0/schema.json",
  "name": "90f45dee40b403843801",
  "position": {
    "x": 0.39281558070066119,
    "y": 0,
    "z": 0,
    "height": 148.55866097611604,
    "width": 172.76365968575575,
    "tabOrder": 26000
  },
  "visual": {
    "visualType": "textbox",
    "objects": {
      "general": [
        {
          "properties": {
            "paragraphs": [
              {
                "textRuns": [
                  {
                    "value": "Hangup SLA, %",
                    "textStyle": {
                      "fontSize": "14pt"
                    }
                  }
                ]
              }
            ]
          }
        }
      ]
    },
    "drillFilterOtherVisuals": true
  },
  "parentGroupName": "0d7bec5e2888ea1da113"
}